kybra_simple_shell/__init__.py
kybra_simple_shell/cli.py
kybra_simple_shell/setup.py
kybra_simple_shell/shell.py
kybra_simple_shell/test_runner.py
kybra_simple_shell/tests/__init__.py
kybra_simple_shell/tests/test_cli.py
kybra_simple_shell/tests/test_shell.py
kybra_simple_shell-0.1.4.dist-info/licenses/LICENSE
kybra_simple_shell-0.1.4.dist-info/METADATA
kybra_simple_shell-0.1.4.dist-info/WHEEL
kybra_simple_shell-0.1.4.dist-info/entry_points.txt
kybra_simple_shell-0.1.4.dist-info/top_level.txt
kybra_simple_shell-0.1.4.dist-info/RECORD
